boj_checker/__init__.py
boj_checker/__main__.py
boj_checker/boj_parser.py
boj_checker/cli.py
boj_checker/config.py
boj_checker/languageinfo.py
boj_checker/runner.py
boj_checker-1.0.0b3.dist-info/LICENSE
boj_checker-1.0.0b3.dist-info/METADATA
boj_checker-1.0.0b3.dist-info/WHEEL
boj_checker-1.0.0b3.dist-info/entry_points.txt
boj_checker-1.0.0b3.dist-info/top_level.txt
boj_checker-1.0.0b3.dist-info/RECORD
